gpt_scraper/__init__.py
gpt_scraper/cli.py
gpt_scraper/gpt_scraper.py
gpt_scraper/html_utils.py
gpt_scraper/prompts.py
gpt_scraper/sandbox.py
gpt_scraper/selenium_utils.py
gpt_scraper/utils.py
gpt_scraper-0.3.2.dist-info/LICENSE
gpt_scraper-0.3.2.dist-info/METADATA
gpt_scraper-0.3.2.dist-info/WHEEL
gpt_scraper-0.3.2.dist-info/entry_points.txt
gpt_scraper-0.3.2.dist-info/top_level.txt
gpt_scraper-0.3.2.dist-info/RECORD
